gamesense/__init__.py
gamesense/gamesense.py
gamesense-0.0.5.dist-info/LICENSE
gamesense-0.0.5.dist-info/METADATA
gamesense-0.0.5.dist-info/WHEEL
gamesense-0.0.5.dist-info/top_level.txt
gamesense-0.0.5.dist-info/RECORD
