Metadata-Version: 2.1
Name: gamesense
Version: 0.0.5
Summary: Library for interacting with SteelSeries GameSense 3.8.x
Home-page: https://github.com/caseybrichardson/gamesense
Author: Casey Richardson
Author-email: caseybrichardson@icloud.com
License: UNKNOWN
Platform: UNKNOWN
Classifier: Programming Language :: Python :: 3
Classifier: License :: OSI Approved :: MIT License
Classifier: Operating System :: OS Independent
License-File: LICENSE
Provides-Extra: async
Requires-Dist: aiohttp ; extra == 'async'
Provides-Extra: sync
Requires-Dist: requests ; extra == 'sync'
